MANIFEST.in
README.rst
setup.py
aliyun_python_sdk_csb.egg-info/PKG-INFO
aliyun_python_sdk_csb.egg-info/SOURCES.txt
aliyun_python_sdk_csb.egg-info/dependency_links.txt
aliyun_python_sdk_csb.egg-info/requires.txt
aliyun_python_sdk_csb.egg-info/top_level.txt
aliyunsdkcsb/__init__.py
aliyunsdkcsb/endpoint.py
aliyunsdkcsb/request/__init__.py
aliyunsdkcsb/request/v20171118/ApproveOrderListRequest.py
aliyunsdkcsb/request/v20171118/CheckSLRDeleteRequest.py
aliyunsdkcsb/request/v20171118/CheckServiceExistRequest.py
aliyunsdkcsb/request/v20171118/CommitSuccessedServicesRequest.py
aliyunsdkcsb/request/v20171118/CreateCredentialsRequest.py
aliyunsdkcsb/request/v20171118/CreateOrderRequest.py
aliyunsdkcsb/request/v20171118/CreateProjectRequest.py
aliyunsdkcsb/request/v20171118/CreateServiceRequest.py
aliyunsdkcsb/request/v20171118/DeleteCasServiceRequest.py
aliyunsdkcsb/request/v20171118/DeleteCredentialsListRequest.py
aliyunsdkcsb/request/v20171118/DeleteOrderListRequest.py
aliyunsdkcsb/request/v20171118/DeleteProjectListRequest.py
aliyunsdkcsb/request/v20171118/DeleteProjectRequest.py
aliyunsdkcsb/request/v20171118/DeleteServiceListRequest.py
aliyunsdkcsb/request/v20171118/DeleteServiceRequest.py
aliyunsdkcsb/request/v20171118/DeleteUnionCasServiceRequest.py
aliyunsdkcsb/request/v20171118/DescribeRegionsRequest.py
aliyunsdkcsb/request/v20171118/FindAllLinkRuleRequest.py
aliyunsdkcsb/request/v20171118/FindApprovalOrderListRequest.py
aliyunsdkcsb/request/v20171118/FindApproveServiceListRequest.py
aliyunsdkcsb/request/v20171118/FindBrokerSLOHisListRequest.py
aliyunsdkcsb/request/v20171118/FindBrokerSLOListRequest.py
aliyunsdkcsb/request/v20171118/FindCredentialStatisticalDataRequest.py
aliyunsdkcsb/request/v20171118/FindCredentialsListRequest.py
aliyunsdkcsb/request/v20171118/FindInstanceListRequest.py
aliyunsdkcsb/request/v20171118/FindInstanceNodeListRequest.py
aliyunsdkcsb/request/v20171118/FindOrderableListRequest.py
aliyunsdkcsb/request/v20171118/FindOrderedListRequest.py
aliyunsdkcsb/request/v20171118/FindOrderedServiceListRequest.py
aliyunsdkcsb/request/v20171118/FindOtherInstanceListRequest.py
aliyunsdkcsb/request/v20171118/FindProjectListRequest.py
